Workbook
Name aporte: 'Controle de FIIs'!$F$16:$F$16
Name dividendos: 'Controle de FIIs'!$F$20:$F$20
Name orcamento_investir: 'Controle de FIIs'!$F$10:$F$10
Name patrimonio_estimado: 'Controle de FIIs'!$F$19:$F$19
Name recomendacao_mensal: 'Controle de FIIs'!$F$12:$F$12
Name renda_mensal: 'Controle de FIIs'!$F$9:$F$9
Name rendimento_carteira: 'Controle de FIIs'!$F$11:$F$11
Name simulacao_12anos: 'Controle de FIIs'!$F$27:$F$27
Name simulacao_15anos: 'Controle de FIIs'!$F$28:$F$28
Name simulacao_18anos: 'Controle de FIIs'!$F$29:$F$29
Name simulacao_21anos: 'Controle de FIIs'!$F$30:$F$30
Name simulacao_24anos: 'Controle de FIIs'!$F$31:$F$31
Name simulacao_27anos: 'Controle de FIIs'!$F$32:$F$32
Name simulacao_30anos: 'Controle de FIIs'!$F$33:$F$33
Name simulacao_3anos: 'Controle de FIIs'!$F$24:$F$24
Name simulacao_6anos: 'Controle de FIIs'!$F$25:$F$25
Name simulacao_9anos: 'Controle de FIIs'!$F$26:$F$26
Name taxa_mensal: 'Controle de FIIs'!$F$18:$F$18
Name tempo: 'Controle de FIIs'!$F$17:$F$17

Sheet Controle de FIIs
B7: CONFIGURAÇÕES
B9: Renda Mensal | F9: 3000
B10: Orçamento para investir | F10: 0.1
B11: Rendimento da carteira | F11: 0.01
B12: Recomendação de investimento mensal | F12: =F9*F10 -> 300
B14: SIMULAÇÃO DE CENÁRIOS
B16: Quanto investidos por mês? | F16: 300
B17: Por quantos anos? | F17: 4
B18: Taxa de rendimento mensal | F18: 0.01079
B19: Patrimônio acumulado | F19: =FV(F18,F17*12,-F16) -> 18736.306
B20: Dividendos mensais | F20: =F19*F11 -> 187.36306
B22: Simulação de Cenários | F22: Dividendos
A24: 3 | B24: ="Em "&A24&" anos" -> Em 3 anos | E24: =FV($F$18,A24*12,-$F$16) -> 13112.512 | F24: =E24*$F$11 -> 131.12512
A25: 6 | B25: ="Em "&A25&" anos" -> Em 6 anos | E25: =FV($F$18,A25*12,-$F$16) -> 32409.06 | F25: =E25*$F$11 -> 324.0906
A26: 9 | B26: ="Em "&A26&" anos" -> Em 9 anos | E26: =FV($F$18,A26*12,-$F$16) -> 60806.118 | F26: =E26*$F$11 -> 608.06118
A27: 12 | B27: ="Em "&A27&" anos" -> Em 12 anos | E27: =FV($F$18,A27*12,-$F$16) -> 102595.61 | F27: =E27*$F$11 -> 1025.9561
A28: 15 | B28: ="Em "&A28&" anos" -> Em 15 anos | E28: =FV($F$18,A28*12,-$F$16) -> 164093.58 | F28: =E28*$F$11 -> 1640.9358
A29: 18 | B29: ="Em "&A29&" anos" -> Em 18 anos | E29: =FV($F$18,A29*12,-$F$16) -> 254594.81 | F29: =E29*$F$11 -> 2545.9481
A30: 21 | B30: ="Em "&A30&" anos" -> Em 21 anos | E30: =FV($F$18,A30*12,-$F$16) -> 387777.64 | F30: =E30*$F$11 -> 3877.7764
A31: 24 | B31: ="Em "&A31&" anos" -> Em 24 anos | E31: =FV($F$18,A31*12,-$F$16) -> 583771.27 | F31: =E31*$F$11 -> 5837.7127
A32: 27 | B32: ="Em "&A32&" anos" -> Em 27 anos | E32: =FV($F$18,A32*12,-$F$16) -> 872198.11 | F32: =E32*$F$11 -> 8721.9811
A33: 30 | B33: ="Em "&A33&" anos" -> Em 30 anos | E33: =FV($F$18,A33*12,-$F$16) -> 1296650.9 | F33: =E33*$F$11 -> 12966.509
B51: Perfil de Investidor | E51: Agressivo
B52: VALOR A SER INVESTIDO POR MÊS | E52: {=aporte} -> 300
B54: TIPO DE FII | E54: PERCENTUAL | F54: VALORES
B55: PAPEL | E55: =VLOOKUP($E$51&B55,Planilha1!$A$1:$D$19,4,FALSE) -> 0.15 | F55: =$E$52*E55 -> 45
B56: RENDA URBANA | E56: =VLOOKUP($E$51&B56,Planilha1!$A$1:$D$19,4,FALSE) -> 0.1 | F56: =$E$52*E56 -> 30
B57: LOGÍSTICA | E57: =VLOOKUP($E$51&B57,Planilha1!$A$1:$D$19,4,FALSE) -> 0.2 | F57: =$E$52*E57 -> 60
B58: SHOPPINGS | E58: =VLOOKUP($E$51&B58,Planilha1!$A$1:$D$19,4,FALSE) -> 0.1 | F58: =$E$52*E58 -> 30
B59: LAGES CORPORATIVAS | E59: =VLOOKUP($E$51&B59,Planilha1!$A$1:$D$19,4,FALSE) -> 0.25 | F59: =$E$52*E59 -> 75
B60: FOFS | E60: =VLOOKUP($E$51&B60,Planilha1!$A$1:$D$19,4,FALSE) -> 0.2 | F60: =$E$52*E60 -> 60

Sheet Planilha1
A1: CHAVE | B1: PERFIL | C1: TIPO | D1: %
A2: =B2&C2 -> ConservadorPAPEL | B2: Conservador | C2: PAPEL | D2: 0.35
A3: =B3&C3 -> ConservadorRENDA URBANA | B3: Conservador | C3: RENDA URBANA | D3: 0.2
A4: =B4&C4 -> ConservadorLOGÍSTICA | B4: Conservador | C4: LOGÍSTICA | D4: 0.15
A5: =B5&C5 -> ConservadorSHOPPINGS | B5: Conservador | C5: SHOPPINGS | D5: 0.15
A6: =B6&C6 -> ConservadorLAGES CORPORATIVAS | B6: Conservador | C6: LAGES CORPORATIVAS | D6: 0.05
A7: =B7&C7 -> ConservadorFOFS | B7: Conservador | C7: FOFS | D7: 0.1
A8: =B8&C8 -> ModeradoPAPEL | B8: Moderado | C8: PAPEL | D8: 0.25
A9: =B9&C9 -> ModeradoRENDA URBANA | B9: Moderado | C9: RENDA URBANA | D9: 0.15
A10: =B10&C10 -> ModeradoLOGÍSTICA | B10: Moderado | C10: LOGÍSTICA | D10: 0.2
A11: =B11&C11 -> ModeradoSHOPPINGS | B11: Moderado | C11: SHOPPINGS | D11: 0.15
A12: =B12&C12 -> ModeradoLAGES CORPORATIVAS | B12: Moderado | C12: LAGES CORPORATIVAS | D12: 0.1
A13: =B13&C13 -> ModeradoFOFS | B13: Moderado | C13: FOFS | D13: 0.15
... A19: =B19&C19 -> AgressivoFOFS | B19: Agressivo | C19: FOFS | D19: 0.2
